scipion_em_xmipp-26.1.0.dist-info/licenses/LICENSE
xmipp3/__init__.py
xmipp3/base.py
xmipp3/bibtex.py
xmipp3/checkProtocolsConf.py
xmipp3/constants.py
xmipp3/logParser.py
xmipp3/programs.py
xmipp3/protocols.conf
xmipp3/protocolsCollectInfo.py
xmipp3/utils.py
xmipp3/version.py
xmipp3/wizards.py
xmipp3/xmipp_logo.png
xmipp3/xmipp_logo_devel.png
xmipp3/convert/__init__.py
xmipp3/convert/convert.py
xmipp3/convert/dataimport.py
xmipp3/convert/io_coordinates.py
xmipp3/legacy/__init__.py
xmipp3/legacy/protocols/__init__.py
xmipp3/legacy/protocols/protocol_angular_resolution_alignment.py
xmipp3/legacy/protocols/protocol_apply_deformation_zernike3d.py
xmipp3/legacy/protocols/protocol_classification_gpuCorr.py
xmipp3/legacy/protocols/protocol_classification_gpuCorr_full.py
xmipp3/legacy/protocols/protocol_classification_gpuCorr_semi.py
xmipp3/legacy/protocols/protocol_classify_kmeans2d.py
xmipp3/legacy/protocols/protocol_deep_align.py
xmipp3/legacy/protocols/protocol_deep_denoising.py
xmipp3/legacy/protocols/protocol_enrich.py
xmipp3/legacy/protocols/protocol_extract_particles_movies.py
xmipp3/legacy/protocols/protocol_kmeans_clustering.py
xmipp3/legacy/protocols/protocol_metaprotocol_create_output.py
xmipp3/legacy/protocols/protocol_metaprotocol_create_subset.py
xmipp3/legacy/protocols/protocol_metaprotocol_discrete_heterogeneity_scheduler.py
xmipp3/legacy/protocols/protocol_metaprotocol_golden_highres.py
xmipp3/legacy/protocols/protocol_mltomo.py
xmipp3/legacy/protocols/protocol_movie_average.py
xmipp3/legacy/protocols/protocol_movie_opticalflow.py
xmipp3/legacy/protocols/protocol_particle_boxsize.py
xmipp3/legacy/protocols/protocol_reconstruct_heterogeneous.py
xmipp3/legacy/protocols/protocol_rotational_spectra.py
xmipp3/legacy/protocols/protocol_screen_deeplearning.py
xmipp3/legacy/protocols/protocol_solid_angles.py
xmipp3/legacy/protocols/protocol_split_volume.py
xmipp3/legacy/protocols/protocol_split_volume_hierarchical_cluster.py
xmipp3/legacy/protocols/protocol_subtract_projection.py
scipion_em_xmipp-26.1.0.dist-info/METADATA
scipion_em_xmipp-26.1.0.dist-info/WHEEL
scipion_em_xmipp-26.1.0.dist-info/entry_points.txt
scipion_em_xmipp-26.1.0.dist-info/top_level.txt
scipion_em_xmipp-26.1.0.dist-info/RECORD
