Metadata-Version: 2.4
Name: scipion-em-xmipp
Version: 26.1.0
Summary: Plugin to use Xmipp programs within the Scipion framework.
Author-email: Oier Lauzirika Zarrabeitia <oierlauzi@bizkaia.eu>, Alberto Garcia Mena <alberto.garcia@cnb.csic.es>, Carlos Oscar Sanchez Sorzano <coss@cnb.csic.es>
License: GNU General Public License v3 (GPLv3)
Project-URL: Homepage, https://github.com/I2PC/scipion-em-xmipp
Project-URL: Issues, https://github.com/I2PC/scipion-em-xmipp/issues
Keywords: scipion electron-microscopy cryo-em structural-biology image-processing scipion-3.0
Requires-Python: >=3.8
License-File: LICENSE
Requires-Dist: scikit-learn>=1.2
Requires-Dist: scikit-image
Requires-Dist: scipy<=1.10.0
Requires-Dist: joblib
Requires-Dist: peppercorn
Requires-Dist: plotter
Requires-Dist: PyWavelets
Requires-Dist: numpy==1.*
Dynamic: license-file
